{
  "status": "ok",
  "code": "0",
  "msg": null,
  "data": [
    {
      "Linesid": "792bd60f-b35c-459e-8a28-6b24e0d341dc",
      "Matchid": "211a812b-57c2-4e03-abb5-02f95f558fbe",
      "Lineid": "16437e41-c921-466a-9fb9-e59eb2004113",
      "Linename": "新能源车",
      "Status": 1,
      "Playercount": 4,
      "Content": "<p>新能源车</p>",
      "Url": "",
      "Summary": "",
      "Pointscount": 10,
      "Condition_Sex": null,
      "Condition_Age": null,
      "Condition_Subline": null,
      "Createtime": "2017-02-07 23:04:48",
      "Price": "0.01"
    }
  ]
}